_CSF.cpython-38-i386-linux-gnu.so
CSF.py
cloth_simulation-1.1.3.dist-info/WHEEL
cloth_simulation-1.1.3.dist-info/LICENSE.txt
cloth_simulation-1.1.3.dist-info/RECORD
cloth_simulation-1.1.3.dist-info/METADATA
cloth_simulation-1.1.3.dist-info/top_level.txt
cloth_simulation.libs/libgomp-65f46eca.so.1.0.0
