Metadata-Version: 2.1
Name: cloth-simulation
Version: 1.1.3
Summary: CSF: Ground Filtering based on Cloth Simulation
Home-page: http://ramm.bnu.edu.cn/projects/CSF/
Author: Jianbo Qi
Maintainer: Romain Janvier
Maintainer-email: romain.janvier@hotmail.fr
License: Apache-2.0
Keywords: LiDAR DTM DSM Classification
License-File: LICENSE.txt
